MANIFEST.in
requirements.txt
setup.py
mediachain/__init__.py
mediachain/indexer/__init__.py
mediachain/indexer/mc_api.py
mediachain/indexer/mc_config.py
mediachain/indexer/mc_datasets.py
mediachain/indexer/mc_eval.py
mediachain/indexer/mc_generic.py
mediachain/indexer/mc_ingest.py
mediachain/indexer/mc_models.py
mediachain/indexer/mc_neighbors.py
mediachain/indexer/mc_normalize.py
mediachain/indexer/mc_rerank.py
mediachain/indexer/mc_simpleclient.py
mediachain/indexer/mc_test.py
mediachain/indexer/mc_web.py
mediachain_indexer.egg-info/PKG-INFO
mediachain_indexer.egg-info/SOURCES.txt
mediachain_indexer.egg-info/dependency_links.txt
mediachain_indexer.egg-info/entry_points.txt
mediachain_indexer.egg-info/pbr.json
mediachain_indexer.egg-info/requires.txt
mediachain_indexer.egg-info/top_level.txt