Metadata-Version: 1.0
Name: mediachain-indexer
Version: 0.0.15
Summary: Mediachain Indexer - Search, Dedupe, Ingestion.
Home-page: http://mediachain.io
Author: Mediachain Labs
Author-email: UNKNOWN
License: UNKNOWN
Platform: UNKNOWN
